{
  "skybox": {
    "filePath": ""
  },

  "models": {
    "opaqueModels": [
      {
        "filePath": "models/bunny/bunny.obj",
        "position": [ 1.0, -1.5, -0.5 ],
        "scale": [ 0.8, 0.8, 0.8 ]
      },
      {
        "filePath": "models/bunny/bunny.obj",
        "position": [ -1.0, -1.5, -0.5 ],
        "scale": [ 0.8, 0.8, 0.8 ]
      }
    ],
    "transparentModels": [
      {
        "filePath": "models/bunny/bunny.obj",
        "position": [ 2.0, -1.5, -1.0 ],
        "scale": [ 0.8, 0.8, 0.8 ],
        "parameters": [ 0.2, 0.2, 0.0, 0.2 ]
      },
      {
        "filePath": "models/bunny/bunny.obj",
        "position": [ 2.0, -1.5, 0.0 ],
        "scale": [ 0.8, 0.8, 0.8 ],
        "parameters": [ 0.0, 0.0, 0.2, 0.8 ]
      },
      {
        "filePath": "models/bunny/bunny.obj",
        "position": [ 0.0, -1.5, -1.0 ],
        "scale": [ 0.8, 0.8, 0.8 ],
        "parameters": [ 0.2, 0.2, 0.0, 0.5 ]
      },
      {
        "filePath": "models/bunny/bunny.obj",
        "position": [ 0.0, -1.5, 0.0 ],
        "scale": [ 0.8, 0.8, 0.8 ],
        "parameters": [ 0.0, 0.0, 0.2, 0.5 ]
      },
      {
        "filePath": "models/bunny/bunny.obj",
        "position": [ -2.0, -1.5, -1.0 ],
        "scale": [ 0.8, 0.8, 0.8 ],
        "parameters": [ 0.2, 0.2, 0.0, 0.9 ]
      },
      {
        "filePath": "models/bunny/bunny.obj",
        "position": [ -2.0, -1.5, 0.0 ],
        "scale": [ 0.8, 0.8, 0.8 ],
        "parameters": [ 0.0, 0.0, 0.2, 0.1 ]
      }
    ]
  }
}